scherkhan/__init__.py
scherkhan/client.py
scherkhan/ws.py
scherkhan/models/__init__.py
scherkhan/models/car.py
scherkhan/models/device.py
scherkhan/models/enums.py
scherkhan/models/user.py
scherkhan/models/websocket.py
scherkhan_auto-0.1.0.dist-info/LICENSE
scherkhan_auto-0.1.0.dist-info/METADATA
scherkhan_auto-0.1.0.dist-info/WHEEL
scherkhan_auto-0.1.0.dist-info/top_level.txt
scherkhan_auto-0.1.0.dist-info/RECORD
