Metadata-Version: 2.1
Name: scherkhan-auto
Version: 0.1.0
Summary: Scher-Khan Auto API client
Home-page: https://github.com/iredun/scherkhan_auto
Author: Ivan Redun
Author-email: redunivan@yandex.ru
Project-URL: Documentation, https://github.com/iredun/scherkhan_auto
Project-URL: Bug Reports, https://github.com/iredun/scherkhan_auto/issues
Project-URL: Source Code, https://github.com/iredun/scherkhan_auto
Keywords: scherkhan,api client
Classifier: Development Status :: 3 - Alpha
Classifier: Intended Audience :: Developers
Classifier: Topic :: Internet :: WWW/HTTP
Classifier: Topic :: Internet :: WWW/HTTP :: Dynamic Content
Classifier: Programming Language :: Python :: 3
Classifier: Programming Language :: Python :: 3.7
Classifier: Programming Language :: Python :: 3.8
Classifier: Programming Language :: Python :: 3.9
Classifier: Programming Language :: Python :: 3 :: Only
Classifier: License :: OSI Approved :: GNU General Public License v3 or later (GPLv3+)
Classifier: Operating System :: OS Independent
Requires-Python: >=3.7
License-File: LICENSE
Requires-Dist: pydantic
Requires-Dist: requests
Requires-Dist: websocket-client
Requires-Dist: rel
Provides-Extra: deploy
Provides-Extra: dev
Requires-Dist: pytest ; extra == 'dev'
Requires-Dist: pytest-env ; extra == 'dev'
Requires-Dist: pytest-cov ; extra == 'dev'
Requires-Dist: requests-mock ; extra == 'dev'
Requires-Dist: flake8 ; extra == 'dev'
Requires-Dist: flake8-docstrings ; extra == 'dev'
Requires-Dist: black ; extra == 'dev'
Requires-Dist: isort ; extra == 'dev'
Requires-Dist: pydantic ; extra == 'dev'
Requires-Dist: requests ; extra == 'dev'
Requires-Dist: websocket-client ; extra == 'dev'
Requires-Dist: rel ; extra == 'dev'
Provides-Extra: docs
Requires-Dist: pytest ; extra == 'docs'
Requires-Dist: pytest-env ; extra == 'docs'
Requires-Dist: pytest-cov ; extra == 'docs'
Requires-Dist: requests-mock ; extra == 'docs'
Requires-Dist: flake8 ; extra == 'docs'
Requires-Dist: flake8-docstrings ; extra == 'docs'
Requires-Dist: black ; extra == 'docs'
Requires-Dist: isort ; extra == 'docs'
Requires-Dist: pydantic ; extra == 'docs'
Requires-Dist: requests ; extra == 'docs'
Requires-Dist: websocket-client ; extra == 'docs'
Requires-Dist: rel ; extra == 'docs'
Provides-Extra: lint
Requires-Dist: flake8 ; extra == 'lint'
Requires-Dist: flake8-docstrings ; extra == 'lint'
Requires-Dist: black ; extra == 'lint'
Requires-Dist: isort ; extra == 'lint'
Provides-Extra: production
Requires-Dist: pydantic ; extra == 'production'
Requires-Dist: requests ; extra == 'production'
Requires-Dist: websocket-client ; extra == 'production'
Requires-Dist: rel ; extra == 'production'
Provides-Extra: test
Requires-Dist: pytest ; extra == 'test'
Requires-Dist: pytest-env ; extra == 'test'
Requires-Dist: pytest-cov ; extra == 'test'
Requires-Dist: requests-mock ; extra == 'test'
